nopokedb/__init__.py
nopokedb/core.py
nopokedb-0.5.1.dist-info/licenses/LICENSE
nopokedb-0.5.1.dist-info/METADATA
nopokedb-0.5.1.dist-info/WHEEL
nopokedb-0.5.1.dist-info/top_level.txt
nopokedb-0.5.1.dist-info/RECORD
