Metadata-Version: 2.4
Name: nopokedb
Version: 0.5.1
Summary: Disk-backed HNSW vector database with SQLite metadata
Author-email: Kashif <me@ifkash.dev>
License: MIT
Requires-Python: >=3.7
License-File: LICENSE
Requires-Dist: hnswlib>=0.7.0
Dynamic: license-file
